cypml/experiments.py
cypml/common/config.py
cypml/common/globals.py
cypml/common/util.py
cypml/run_workflow/combine_features.py
cypml/run_workflow/compare_with_mcyfs.py
cypml/run_workflow/load_saved_features.py
cypml/run_workflow/load_saved_predictions.py
cypml/run_workflow/run_data_preprocessing.py
cypml/run_workflow/run_data_summary.py
cypml/run_workflow/run_feature_design.py
cypml/run_workflow/run_machine_learning.py
cypml/run_workflow/run_train_test_split.py
cypml/run_workflow/run_trend_feature_design.py
cypml/tests/test_algorithm_evaluation.py
cypml/tests/test_data_loading.py
cypml/tests/test_data_preprocessing.py
cypml/tests/test_data_summary.py
cypml/tests/test_feature_design.py
cypml/tests/test_feature_selection.py
cypml/tests/test_train_test_split.py
cypml/tests/test_util.py
cypml/tests/test_yield_trend.py
cypml/workflow/algorithm_evaluation.py
cypml/workflow/crop_calendar.py
cypml/workflow/data_loading.py
cypml/workflow/data_preprocessing.py
cypml/workflow/data_summary.py
cypml/workflow/feature_design.py
cypml/workflow/feature_selection.py
cypml/workflow/train_test_split.py
cypml/workflow/yield_trend.py
cypml-1.2.6.dist-info/METADATA
cypml-1.2.6.dist-info/WHEEL
cypml-1.2.6.dist-info/top_level.txt
cypml-1.2.6.dist-info/RECORD
