Metadata-Version: 2.1
Name: cypml
Version: 1.2.6
Summary: Machine learning baseline for crop yield forecasting
Home-page: https://github.com/BigDataWUR/MLforCropYieldForecasting
Author: Dilli Paudel
Author-email: dilli.paudel@wur.nl
License: UNKNOWN
Project-URL: Paper, https://doi.org/10.1016/j.agsy.2020.103016
Project-URL: Sample data, https://doi.org/10.5281/zenodo.4312941
Project-URL: Source, https://github.com/BigDataWUR/MLforCropYieldForecasting
Keywords: machine learning,crop yield,reusability
Platform: UNKNOWN
Classifier: Development Status :: 3 - Alpha
Classifier: Intended Audience :: Science/Research
Classifier: Topic :: Scientific/Engineering
Classifier: License :: Freely Distributable
Classifier: Programming Language :: Python :: 3
Classifier: Programming Language :: Python :: 3.6
Classifier: Programming Language :: Python :: 3.7
Classifier: Programming Language :: Python :: 3.8
Classifier: Programming Language :: Python :: 3.9
Classifier: Programming Language :: Python :: 3 :: Only
Requires-Python: >=3.6, <4
Requires-Dist: joblibspark
